OpenRS/__init__.py
OpenRS/compare.py
OpenRS/flexure_widget.py
OpenRS/main.py
OpenRS/model_viewer.py
OpenRS/open_rs_common.py
OpenRS/open_rs_hdf5_io.py
OpenRS/point_selector.py
OpenRS/return_disp.py
OpenRS/sgv.py
OpenRS/viewer.py
OpenRS/examples/U_elastic_run.vtu
OpenRS/examples/U_elastic_run_ccx.vtu
OpenRS/examples/U_elastic_run_ccx_fid.txt
OpenRS/examples/U_elastic_run_fid.txt
OpenRS/examples/U_plastic_run.vtu
OpenRS/examples/__init__.py
OpenRS/generate/U_elastic_mesh_only.inp
OpenRS/generate/__init__.py
OpenRS/generate/build_model.py
OpenRS/generate/build_model_plastic.py
OpenRS/generate/frd_access.py
OpenRS/generate/odb_access.py
OpenRS/generate/odb_access_plastic.py
OpenRS/generate/packager.py
OpenRS/generate/packager_ccx.py
OpenRS/generate/packager_plastic.py
OpenRS/geometry/Arch_AM.STL
OpenRS/geometry/Arch_BA_xx.STL
OpenRS/geometry/U_elastic.scad
OpenRS/geometry/U_elastic.stl
OpenRS/geometry/U_elastic_exp_fid.STEP
OpenRS/geometry/U_elastic_imp_fid.STEP
OpenRS/geometry/U_plastic.stl
OpenRS/geometry/__init__.py
OpenRS/meta/Logo.png
OpenRS/meta/OpenRS_icon.png
OpenRS/meta/OpenRSconfig.yml
OpenRS/meta/__init__.py
OpenRS/meta/flexure_pnts.png
OpenRS-0.3.2.dist-info/LICENSE
OpenRS-0.3.2.dist-info/METADATA
OpenRS-0.3.2.dist-info/WHEEL
OpenRS-0.3.2.dist-info/top_level.txt
OpenRS-0.3.2.dist-info/RECORD
