Metadata-Version: 2.1
Name: OpenRS
Version: 0.3.2
Summary: Open Residual Stress analysis suite
Home-page: https://github.com/majroy/OpenRS
Author: M J Roy
Author-email: matthew.roy@manchester.ac.uk
License: Creative Commons Attribution-Noncommercial-Share Alike license
Platform: UNKNOWN
Classifier: Environment :: Win32 (MS Windows)
Classifier: Topic :: Scientific/Engineering :: Visualization
Classifier: License :: OSI Approved :: GNU General Public License v3 or later (GPLv3+)
Classifier: Operating System :: Microsoft :: Windows :: Windows 7
Classifier: Programming Language :: Python :: 3.8
Classifier: Intended Audience :: End Users/Desktop
Classifier: Natural Language :: English
Requires-Python: >=3.8
License-File: LICENSE
Requires-Dist: numpy
Requires-Dist: vtk
Requires-Dist: matplotlib
Requires-Dist: PyQt5 (>=5.13)
Requires-Dist: h5py
Requires-Dist: pyyaml (>=5.0)
Requires-Dist: scipy
